plopy/__init__.py
plopy/__main__.py
plopy/test-data.txt
plopy/ui/__init__.py
plopy/ui/icon_16x16.png
plopy/ui/icon_24x24.png
plopy/ui/ui_dialog_load_advanced.py
plopy/ui/ui_dialog_view_array.py
plopy/ui/ui_dialog_view_file.py
plopy/ui/ui_mainwindow.py
plopy/ui/ui_options_axes.py
plopy/ui/ui_options_axes_add.py
plopy/ui/ui_options_axes_lim.py
plopy/ui/ui_options_figure.py
plopy/ui/ui_options_line.py
plopy/ui/ui_options_parser.py
plopy/ui/ui_options_plot.py
plopy-1.7.0.dist-info/licenses/LICENSE
plopy-1.7.0.dist-info/METADATA
plopy-1.7.0.dist-info/WHEEL
plopy-1.7.0.dist-info/top_level.txt
plopy-1.7.0.dist-info/RECORD
