Metadata-Version: 2.4
Name: plopy
Version: 1.7.0
Summary: GUI for matplotlib graphing
Home-page: https://github.com/Finnventor/plopy
Author: Finnventor
Classifier: Programming Language :: Python :: 3
Classifier: License :: OSI Approved :: GNU General Public License v3 (GPLv3)
Classifier: Operating System :: OS Independent
License-File: LICENSE
Requires-Dist: python-dateutil>=2.8.1
Requires-Dist: PySide6-Essentials
Requires-Dist: matplotlib
Dynamic: author
Dynamic: classifier
Dynamic: description
Dynamic: home-page
Dynamic: license-file
Dynamic: requires-dist
Dynamic: summary
